onegov.ballot-3.10.1-py3.6-nspkg.pth
onegov/ballot/.gitignore
onegov/ballot/__init__.py
onegov/ballot/upgrade.py
onegov/ballot/collections/__init__.py
onegov/ballot/collections/ballots.py
onegov/ballot/collections/candidates.py
onegov/ballot/collections/election_compounds.py
onegov/ballot/collections/elections.py
onegov/ballot/collections/lists.py
onegov/ballot/collections/votes.py
onegov/ballot/models/__init__.py
onegov/ballot/models/mixins.py
onegov/ballot/models/election/__init__.py
onegov/ballot/models/election/association.py
onegov/ballot/models/election/candidate.py
onegov/ballot/models/election/candidate_result.py
onegov/ballot/models/election/election.py
onegov/ballot/models/election/election_compound.py
onegov/ballot/models/election/election_result.py
onegov/ballot/models/election/list.py
onegov/ballot/models/election/list_connection.py
onegov/ballot/models/election/list_result.py
onegov/ballot/models/election/mixins.py
onegov/ballot/models/election/panachage_result.py
onegov/ballot/models/election/party_result.py
onegov/ballot/models/election/proporz_election.py
onegov/ballot/models/vote/__init__.py
onegov/ballot/models/vote/ballot.py
onegov/ballot/models/vote/ballot_result.py
onegov/ballot/models/vote/complex_vote.py
onegov/ballot/models/vote/mixins.py
onegov/ballot/models/vote/vote.py
onegov/ballot/tests/conftest.py
onegov/ballot/tests/collections/test_ballots.py
onegov/ballot/tests/collections/test_candidates.py
onegov/ballot/tests/collections/test_elections.py
onegov/ballot/tests/collections/test_lists.py
onegov/ballot/tests/collections/test_votes.py
onegov/ballot/tests/models/test_candidate.py
onegov/ballot/tests/models/test_election.py
onegov/ballot/tests/models/test_election_compound.py
onegov/ballot/tests/models/test_list.py
onegov/ballot/tests/models/test_proporz_election.py
onegov/ballot/tests/models/test_vote.py
onegov.ballot-3.10.1.dist-info/METADATA
onegov.ballot-3.10.1.dist-info/WHEEL
onegov.ballot-3.10.1.dist-info/entry_points.txt
onegov.ballot-3.10.1.dist-info/namespace_packages.txt
onegov.ballot-3.10.1.dist-info/top_level.txt
onegov.ballot-3.10.1.dist-info/RECORD
